irene_sankey/__init__.py
irene_sankey/core/__init__.py
irene_sankey/core/traverse.py
irene_sankey/plots/__init__.py
irene_sankey/plots/sankey.py
irene_sankey/utils/__init__.py
irene_sankey/utils/performance.py
irene_sankey/utils/utils.py
irene_sankey-2.0.1.dist-info/LICENSE
irene_sankey-2.0.1.dist-info/METADATA
irene_sankey-2.0.1.dist-info/WHEEL
irene_sankey-2.0.1.dist-info/RECORD
