Metadata-Version: 2.3
Name: irene-sankey
Version: 2.0.1
Summary: A package for generating source-target pair and node map from polars and pandas DataFrames for Sankey flow diagrams
License: MIT
Author: FOX Techniques
Author-email: ali.nabbi@fox-techniques.com
Requires-Python: >=3.10,<4.0
Classifier: License :: OSI Approved :: MIT License
Classifier: Programming Language :: Python :: 3
Classifier: Programming Language :: Python :: 3.10
Classifier: Programming Language :: Python :: 3.11
Classifier: Programming Language :: Python :: 3.12
Classifier: Programming Language :: Python :: 3.13
Requires-Dist: mkdocs-material (>=9.5.43,<10.0.0)
Requires-Dist: numpy (>=1.24) ; python_version >= "3.10"
Requires-Dist: numpy (>=1.24,<2.0) ; python_version < "3.10"
Requires-Dist: pandas (>=1.5) ; python_version >= "3.10"
Requires-Dist: pandas (>=1.5,<2.0) ; python_version < "3.10"
Requires-Dist: plotly (>=5.24.1,<6.0.0)
Requires-Dist: polars (>=1.24.0,<2.0.0)
Requires-Dist: requests (>=2.32.3,<3.0.0)
Project-URL: Homepage, https://github.com/fox-techniques/irene-sankey
